{"nodes": [{"id": "build_with_ai_prompt_template", "label": "Build With AI Prompt Template", "file_type": "document", "source_file": "41-build-with-ai-playbook/templates/build-with-ai-prompt-template.md", "source_location": null, "source_url": null, "captured_at": null, "author": null, "contributor": null}, {"id": "build_with_ai_prompt_template", "label": "Build With AI Prompt Template", "file_type": "document", "source_file": "41-build-with-ai-playbook/templates/build-with-ai-prompt-template.md", "source_location": null, "source_url": null, "captured_at": null, "author": null, "contributor": null}], "edges": [{"source": "build_with_ai_prompt_template", "target": "41_build_with_ai_playbook", "relation": "implements", "confidence": "EXTRACTED", "confidence_score": 1.0, "source_file": "41-build-with-ai-playbook/templates/build-with-ai-prompt-template.md", "source_location": null, "weight": 1.0}], "hyperedges": []}