{"nodes": [{"id": "zhc_tag_prefix_protocol", "label": "ZHC Tag-Prefix Protocol", "file_type": "document", "source_file": "38-conversational-ai-system/protocols/zhc-tag-prefix-protocol.md", "source_location": null, "source_url": null, "captured_at": null, "author": null, "contributor": null}, {"id": "zhc_tag_prefix_rule", "label": "ZHC Tag Prefix Rule", "file_type": "concept", "source_file": "38-conversational-ai-system/protocols/zhc-tag-prefix-protocol.md", "source_location": null, "source_url": null, "captured_at": null, "author": null, "contributor": null}], "edges": [{"source": "zhc_tag_prefix_protocol", "target": "zhc_tag_prefix_rule", "relation": "references", "confidence": "EXTRACTED", "confidence_score": 1.0, "source_file": "38-conversational-ai-system/protocols/zhc-tag-prefix-protocol.md", "source_location": null, "weight": 1.0}, {"source": "zhc_tag_prefix_protocol", "target": "zhc_pixel_protocol", "relation": "conceptually_related_to", "confidence": "INFERRED", "confidence_score": 0.9, "source_file": "38-conversational-ai-system/protocols/zhc-tag-prefix-protocol.md", "source_location": null, "weight": 0.9}], "hyperedges": []}